.travis.yml
AUTHORS
ChangeLog
LICENSE
README.md
requirements.txt
setup.cfg
setup.py
test-requirements.txt
tox.ini
qg/__init__.py
qg.web.egg-info/PKG-INFO
qg.web.egg-info/SOURCES.txt
qg.web.egg-info/dependency_links.txt
qg.web.egg-info/not-zip-safe
qg.web.egg-info/pbr.json
qg.web.egg-info/requires.txt
qg.web.egg-info/top_level.txt
qg/web/__init__.py
qg/web/glogging.py
qg/web/app/__init__.py
qg/web/app/flaskapp.py
qg/web/app/wsgiapp.py
tests/__init__.py
tests/unit/__init__.py
tests/unit/app/__init__.py
tests/unit/app/test_baseurl.py