Metadata-Version: 1.1
Name: qg.web
Version: 0.1.3
Summary: qg.web
Home-page: https://github.com/QunarOPS/qg.web
Author: QunarOPS
Author-email: jaypei97159@gmail.com,jianingy.yang@gmail.com
License: UNKNOWN
Platform: UNKNOWN
Classifier: Development Status :: 1 - Planning
Classifier: Environment :: MacOS X
Classifier: Environment :: Console
Classifier: Environment :: No Input/Output (Daemon)
Classifier: Environment :: Other Environment
Classifier: Environment :: Plugins
Classifier: Environment :: Win32 (MS Windows)
Classifier: Intended Audience :: Developers
Classifier: Intended Audience :: Information Technology
Classifier: Intended Audience :: System Administrators
Classifier: License :: OSI Approved
Classifier: Natural Language :: Chinese (Simplified)
Classifier: Natural Language :: English
Classifier: Operating System :: POSIX
Classifier: Operating System :: Unix
Classifier: Operating System :: MacOS
Classifier: Operating System :: Microsoft
Classifier: Programming Language :: Python
Classifier: Topic :: Software Development
